{
  "name": "iframe",
  "version": "1.4.3",
  "license": "MIT",
  "homepage": "https://github.com/hacklover/owd-sample",
  "author": {
    "name": "hacklover",
    "url": "https://github.com/hacklover"
  },
  "autostart": true,
  "singleton": true,
  "commands": true,
  "windows": [
    {
      "name": "WindowSnake3D",
      "title": "Web Plays Snake",
      "icon": "mdi-web",
      "color": "#37a5c4",
      "externalUrl": "https://snake.hacklover.net",
      "iframeUrl": "https://snake.hacklover.net/?host=https://hacklover-snake-server.herokuapp.com",
      "window": {
        "menu": true,
        "closed": true,
        "minimized": false,
        "resizable": false,
        "width": 728,
        "height": 510,
        "x": 0,
        "y": 0,
        "z": 0
      }
    }
  ]
}
